tvrip/__init__.py
tvrip/cmdline.py
tvrip/const.py
tvrip/database.py
tvrip/episodemap.py
tvrip/main.py
tvrip/multipart.py
tvrip/richrst.py
tvrip/ripcmd.py
tvrip/ripper.py
tvrip/tvdb.py
tvrip/docs/cmd_automap.rst
tvrip/docs/cmd_config.rst
tvrip/docs/cmd_disc.rst
tvrip/docs/cmd_duplicate.rst
tvrip/docs/cmd_episode.rst
tvrip/docs/cmd_episodes.rst
tvrip/docs/cmd_exit.rst
tvrip/docs/cmd_help.rst
tvrip/docs/cmd_map.rst
tvrip/docs/cmd_play.rst
tvrip/docs/cmd_program.rst
tvrip/docs/cmd_programs.rst
tvrip/docs/cmd_quit.rst
tvrip/docs/cmd_rip.rst
tvrip/docs/cmd_scan.rst
tvrip/docs/cmd_season.rst
tvrip/docs/cmd_seasons.rst
tvrip/docs/cmd_set.rst
tvrip/docs/cmd_title.rst
tvrip/docs/cmd_unmap.rst
tvrip/docs/cmd_unrip.rst
tvrip/docs/var_api.rst
tvrip/docs/var_api_key.rst
tvrip/docs/var_atomicparsley.rst
tvrip/docs/var_audio_all.rst
tvrip/docs/var_audio_encoding.rst
tvrip/docs/var_audio_langs.rst
tvrip/docs/var_audio_mix.rst
tvrip/docs/var_decomb.rst
tvrip/docs/var_duplicates.rst
tvrip/docs/var_duration.rst
tvrip/docs/var_dvdnav.rst
tvrip/docs/var_handbrake.rst
tvrip/docs/var_id_template.rst
tvrip/docs/var_max_resolution.rst
tvrip/docs/var_mkvpropedit.rst
tvrip/docs/var_output_format.rst
tvrip/docs/var_source.rst
tvrip/docs/var_subtitle_all.rst
tvrip/docs/var_subtitle_default.rst
tvrip/docs/var_subtitle_format.rst
tvrip/docs/var_subtitle_langs.rst
tvrip/docs/var_target.rst
tvrip/docs/var_temp.rst
tvrip/docs/var_template.rst
tvrip/docs/var_video_style.rst
tvrip/docs/var_vlc.rst
tvrip/sql/create_db.sql
tvrip/sql/migrate_db_1_to_2.sql
tvrip-3.3.dist-info/LICENSE.txt
tvrip-3.3.dist-info/METADATA
tvrip-3.3.dist-info/WHEEL
tvrip-3.3.dist-info/entry_points.txt
tvrip-3.3.dist-info/top_level.txt
tvrip-3.3.dist-info/RECORD
