Metadata-Version: 2.1
Name: tvrip
Version: 3.3
Summary: Extract and transcode TV series from DVD or Bluray
Home-page: UNKNOWN
Author: Dave Jones
Author-email: dave@waveform.org.uk
License: UNKNOWN
Project-URL: Source Code, https://github.com/waveform80/tvrip
Project-URL: Issue Tracker, https://github.com/waveform80/tvrip/issues
Keywords: handbrake dvd bluray tv rip
Platform: UNKNOWN
Classifier: Development Status :: 5 - Production/Stable
Classifier: Environment :: Console
Classifier: Intended Audience :: End Users/Desktop
Classifier: License :: OSI Approved :: GNU General Public License v3 or later (GPLv3+)
Classifier: Operating System :: POSIX :: Linux
Classifier: Operating System :: MacOS :: MacOS X
Classifier: Programming Language :: Python :: 3
Classifier: Programming Language :: Python :: 3.10
Classifier: Programming Language :: Python :: 3.11
Classifier: Programming Language :: Python :: 3.12
Classifier: Topic :: Multimedia :: Video :: Conversion
Requires-Python: >=3.10
License-File: LICENSE.txt
Requires-Dist: docutils
Requires-Dist: requests
Requires-Dist: rich
Requires-Dist: setuptools
Requires-Dist: sqlalchemy (>=1.4)
Provides-Extra: doc
Requires-Dist: sphinx ; extra == 'doc'
Requires-Dist: sphinx-rtd-theme ; extra == 'doc'
Provides-Extra: test
Requires-Dist: pytest ; extra == 'test'
Requires-Dist: pytest-cov ; extra == 'test'
